oe_common/__init__.py
oe_common/oe_common.py
oe_common-1.7.1.3.dist-info/LICENSE.txt
oe_common-1.7.1.3.dist-info/METADATA
oe_common-1.7.1.3.dist-info/WHEEL
oe_common-1.7.1.3.dist-info/top_level.txt
oe_common-1.7.1.3.dist-info/RECORD
