Metadata-Version: 2.1
Name: oe_common
Version: 1.7.1.3
Summary: OeCommon
Home-page: https://github.com/jok4r/oe_common
Author: Dmitry Yakovlev
Author-email: info@overhosting.ru
License: MIT
Requires-Python: >=3.6
License-File: LICENSE.txt
Requires-Dist: requests
Requires-Dist: psutil
